arbi/__init__.py
arbi/_base_client.py
arbi/_client.py
arbi/_compat.py
arbi/_constants.py
arbi/_exceptions.py
arbi/_files.py
arbi/_models.py
arbi/_qs.py
arbi/_resource.py
arbi/_response.py
arbi/_streaming.py
arbi/_types.py
arbi/_version.py
arbi/py.typed
arbi/_utils/__init__.py
arbi/_utils/_compat.py
arbi/_utils/_datetime_parse.py
arbi/_utils/_json.py
arbi/_utils/_logs.py
arbi/_utils/_proxy.py
arbi/_utils/_reflection.py
arbi/_utils/_resources_proxy.py
arbi/_utils/_streams.py
arbi/_utils/_sync.py
arbi/_utils/_transform.py
arbi/_utils/_typing.py
arbi/_utils/_utils.py
arbi/lib/.keep
arbi/resources/__init__.py
arbi/resources/api/__init__.py
arbi/resources/api/api.py
arbi/resources/api/assistant.py
arbi/resources/api/configs.py
arbi/resources/api/health.py
arbi/resources/api/notifications.py
arbi/resources/api/tag.py
arbi/resources/api/workspace.py
arbi/resources/api/conversation/__init__.py
arbi/resources/api/conversation/conversation.py
arbi/resources/api/conversation/user.py
arbi/resources/api/document/__init__.py
arbi/resources/api/document/doctag.py
arbi/resources/api/document/document.py
arbi/resources/api/user/__init__.py
arbi/resources/api/user/contacts.py
arbi/resources/api/user/settings.py
arbi/resources/api/user/subscription.py
arbi/resources/api/user/user.py
arbi/types/__init__.py
arbi/types/chunk.py
arbi/types/chunk_metadata.py
arbi/types/chunk_metadata_param.py
arbi/types/chunk_param.py
arbi/types/api/__init__.py
arbi/types/api/assistant_query_params.py
arbi/types/api/assistant_retrieve_params.py
arbi/types/api/chunker_config_param.py
arbi/types/api/config_create_params.py
arbi/types/api/config_create_response.py
arbi/types/api/config_delete_response.py
arbi/types/api/config_get_versions_response.py
arbi/types/api/config_retrieve_response.py
arbi/types/api/conversation_delete_message_response.py
arbi/types/api/conversation_delete_response.py
arbi/types/api/conversation_retrieve_message_response.py
arbi/types/api/conversation_retrieve_threads_response.py
arbi-0.24.0.dist-info/METADATA
arbi-0.24.0.dist-info/WHEEL
arbi-0.24.0.dist-info/licenses/LICENSE
arbi-0.24.0.dist-info/RECORD
